siva_poetry/__init__.py
siva_poetry/__main__.py
siva_poetry/config/cities.yaml
siva_poetry/model/data.pickle
siva_poetry/simple.py
siva_poetry-2.0.1.dist-info/entry_points.txt
siva_poetry-2.0.1.dist-info/WHEEL
siva_poetry-2.0.1.dist-info/METADATA
siva_poetry-2.0.1.dist-info/RECORD
