Metadata-Version: 2.1
Name: siva-poetry
Version: 2.0.1
Summary: Simple project
Author: siva
Author-email: sivakon@outlook.com
Requires-Python: >=3.7,<4.0
Classifier: Programming Language :: Python :: 3
Classifier: Programming Language :: Python :: 3.7
Requires-Dist: pendulum (>=2.0,<3.0)
Requires-Dist: pyyaml (>=5.1,<6.0)
